pillow_svg/__init__.py
pillow_svg/SvgImagePlugin.py
pillow_svg-0.1.0.dist-info/WHEEL
pillow_svg-0.1.0.dist-info/METADATA
pillow_svg-0.1.0.dist-info/RECORD
