Metadata-Version: 2.1
Name: pillow-svg
Version: 0.1.0
Summary: 
Home-page: https://github.com/gribbg/pillow_svg
Author: djkcyl
Author-email: cyl@cyllive.cn
Classifier: Programming Language :: Python :: 2
Classifier: Programming Language :: Python :: 2.7
Classifier: Programming Language :: Python :: 3
Classifier: Programming Language :: Python :: 3.10
Classifier: Programming Language :: Python :: 3.4
Classifier: Programming Language :: Python :: 3.5
Classifier: Programming Language :: Python :: 3.6
Classifier: Programming Language :: Python :: 3.7
Classifier: Programming Language :: Python :: 3.8
Classifier: Programming Language :: Python :: 3.9
Requires-Dist: Pillow (>=8.4.0,<9.0.0)
Project-URL: Repository, https://github.com/gribbg/pillow_svg
